claudelint/__init__.py
claudelint/__main__.py
claudelint/config.py
claudelint/context.py
claudelint/linter.py
claudelint/rule.py
claudelint/rules/builtin/__init__.py
claudelint/rules/builtin/agents.py
claudelint/rules/builtin/command_format.py
claudelint/rules/builtin/hooks.py
claudelint/rules/builtin/marketplace.py
claudelint/rules/builtin/mcp.py
claudelint/rules/builtin/plugin_structure.py
claudelint/rules/builtin/skills.py
claudelint-0.3.3.dist-info/licenses/LICENSE
claudelint-0.3.3.dist-info/METADATA
claudelint-0.3.3.dist-info/WHEEL
claudelint-0.3.3.dist-info/entry_points.txt
claudelint-0.3.3.dist-info/top_level.txt
claudelint-0.3.3.dist-info/RECORD
