Metadata-Version: 2.4
Name: claudelint
Version: 0.3.3
Summary: A configurable, rule-based linter for Claude Code plugins
Author-email: Stephen Benjamin <stephen@bitbin.de>
License: Apache-2.0
Project-URL: Homepage, https://github.com/stbenjam/claudelint
Project-URL: Documentation, https://github.com/stbenjam/claudelint#readme
Project-URL: Repository, https://github.com/stbenjam/claudelint
Project-URL: Issues, https://github.com/stbenjam/claudelint/issues
Keywords: claude,claude-code,linter,plugin,validation
Classifier: Development Status :: 4 - Beta
Classifier: Intended Audience :: Developers
Classifier: License :: OSI Approved :: Apache Software License
Classifier: Programming Language :: Python :: 3
Classifier: Programming Language :: Python :: 3.8
Classifier: Programming Language :: Python :: 3.9
Classifier: Programming Language :: Python :: 3.10
Classifier: Programming Language :: Python :: 3.11
Classifier: Programming Language :: Python :: 3.12
Classifier: Topic :: Software Development :: Quality Assurance
Classifier: Topic :: Software Development :: Testing
Requires-Python: >=3.8
License-File: LICENSE
Requires-Dist: PyYAML>=6.0
Provides-Extra: dev
Requires-Dist: pytest>=7.0; extra == "dev"
Requires-Dist: pytest-cov>=4.0; extra == "dev"
Requires-Dist: black>=23.0; extra == "dev"
Requires-Dist: flake8>=6.0; extra == "dev"
Requires-Dist: mypy>=1.0; extra == "dev"
Dynamic: license-file
